ordinary.py
ordinary-2.1.0.dist-info/LICENSE
ordinary-2.1.0.dist-info/METADATA
ordinary-2.1.0.dist-info/WHEEL
ordinary-2.1.0.dist-info/top_level.txt
ordinary-2.1.0.dist-info/RECORD
