Metadata-Version: 2.1
Name: ordinary
Version: 2.1.0
Summary: Encoding tools for a largely compatible encryption system based on the interpolation of character and ordinal values.
Home-page: https://github.com/Kreusada/Ordinary
Author: Kreusada
Author-email: kreusadaprojects@gmail.com
License: UNKNOWN
Platform: UNKNOWN
Classifier: License :: OSI Approved :: MIT License
Classifier: Operating System :: OS Independent
Classifier: Natural Language :: English
Classifier: Programming Language :: Python :: 3.6
Classifier: Programming Language :: Python :: 3.7
Classifier: Programming Language :: Python :: 3.8
Classifier: Programming Language :: Python :: 3.9
Classifier: Programming Language :: Python :: 3.10
License-File: LICENSE
